analytic/__init__.py
analytic/column.py
analytic/convertDT.py
analytic/mapp.py
analytic/reduce.py
analytic-1.0.dist-info/METADATA
analytic-1.0.dist-info/RECORD
analytic-1.0.dist-info/WHEEL
analytic-1.0.dist-info/top_level.txt
