Metadata-Version: 2.1
Name: analytic
Version: 1.0
Summary: A python library for fetching, cleaning & sorting the CSV file
Home-page: https://github.com/dishitpala/analytic
Author: Dishit Pala
Author-email: dishitpala@gmail.com
License: UNKNOWN
Platform: UNKNOWN
Classifier: Programming Language :: Python :: 3
Classifier: License :: OSI Approved :: MIT License
Classifier: Operating System :: OS Independent
